fastapi_role/__init__.py
fastapi_role/base.py
fastapi_role/exception.py
fastapi_role/py.typed
fastapi_role/rbac.py
fastapi_role/rbac_service.py
fastapi_role/core/composition.py
fastapi_role/core/config.py
fastapi_role/core/ownership.py
fastapi_role/core/roles.py
fastapi_role/helpers/__init__.py
fastapi_role/protocols/__init__.py
fastapi_role/protocols/providers.py
fastapi_role/protocols/user.py
fastapi_role/providers/__init__.py
fastapi_role/providers/default_ownership.py
fastapi_role-0.1.0.dev1.dist-info/METADATA
fastapi_role-0.1.0.dev1.dist-info/WHEEL
fastapi_role-0.1.0.dev1.dist-info/licenses/LICENSE
fastapi_role-0.1.0.dev1.dist-info/RECORD
